[
  {
    "id": "bodoglimt",
    "navn": "FK Bodø/Glimt",
    "kortnavn": "BOD",
    "by": "Bodø",
    "divisjon": "Eliteserien",
    "sone": null,
    "stadion_navn": "Aspmyra Stadion",
    "stadion_kapasitet": 7802,
    "stadion_standard": 4,
    "stadion_byggeaar": 1998,
    "rivaler": ["tromso", "rosenborg"],
    "historisk_styrke": 18
  },
  {
    "id": "rosenborg",
    "navn": "Rosenborg BK",
    "kortnavn": "RBK",
    "by": "Trondheim",
    "divisjon": "Eliteserien",
    "sone": null,
    "stadion_navn": "Lerkendal Stadion",
    "stadion_kapasitet": 21421,
    "stadion_standard": 5,
    "stadion_byggeaar": 1947,
    "rivaler": ["molde", "bodoglimt", "brann"],
    "historisk_styrke": 20
  },
  {
    "id": "molde",
    "navn": "Molde FK",
    "kortnavn": "MOL",
    "by": "Molde",
    "divisjon": "Eliteserien",
    "sone": null,
    "stadion_navn": "Aker Stadion",
    "stadion_kapasitet": 11800,
    "stadion_standard": 4,
    "stadion_byggeaar": 1998,
    "rivaler": ["rosenborg", "aalesund", "kristiansund"],
    "historisk_styrke": 18
  },
  {
    "id": "brann",
    "navn": "SK Brann",
    "kortnavn": "BRA",
    "by": "Bergen",
    "divisjon": "Eliteserien",
    "sone": null,
    "stadion_navn": "Brann Stadion",
    "stadion_kapasitet": 17049,
    "stadion_standard": 5,
    "stadion_byggeaar": 1919,
    "rivaler": ["rosenborg", "viking", "valerenga"],
    "historisk_styrke": 18
  },
  {
    "id": "viking",
    "navn": "Viking FK",
    "kortnavn": "VIK",
    "by": "Stavanger",
    "divisjon": "Eliteserien",
    "sone": null,
    "stadion_navn": "SR-Bank Arena",
    "stadion_kapasitet": 15900,
    "stadion_standard": 5,
    "stadion_byggeaar": 2004,
    "rivaler": ["brann", "sandnesulf", "bryne"],
    "historisk_styrke": 18
  },
  {
    "id": "lillestrom",
    "navn": "Lillestrøm SK",
    "kortnavn": "LSK",
    "by": "Lillestrøm",
    "divisjon": "Eliteserien",
    "sone": null,
    "stadion_navn": "Åråsen Stadion",
    "stadion_kapasitet": 12250,
    "stadion_standard": 4,
    "stadion_byggeaar": 1951,
    "rivaler": ["valerenga", "strommen"],
    "historisk_styrke": 17
  },
  {
    "id": "valerenga",
    "navn": "Vålerenga IF",
    "kortnavn": "VIF",
    "by": "Oslo",
    "divisjon": "Eliteserien",
    "sone": null,
    "stadion_navn": "Intility Arena",
    "stadion_kapasitet": 16555,
    "stadion_standard": 5,
    "stadion_byggeaar": 2017,
    "rivaler": ["lillestrom", "brann", "lyn"],
    "historisk_styrke": 17
  },
  {
    "id": "fredrikstad",
    "navn": "Fredrikstad FK",
    "kortnavn": "FFK",
    "by": "Fredrikstad",
    "divisjon": "Eliteserien",
    "sone": null,
    "stadion_navn": "Fredrikstad Stadion",
    "stadion_kapasitet": 12560,
    "stadion_standard": 4,
    "stadion_byggeaar": 2006,
    "rivaler": ["sarpsborg08", "moss"],
    "historisk_styrke": 16
  },
  {
    "id": "sarpsborg08",
    "navn": "Sarpsborg 08",
    "kortnavn": "S08",
    "by": "Sarpsborg",
    "divisjon": "Eliteserien",
    "sone": null,
    "stadion_navn": "Sarpsborg Stadion",
    "stadion_kapasitet": 8022,
    "stadion_standard": 4,
    "stadion_byggeaar": 1930,
    "rivaler": ["fredrikstad", "odd"],
    "historisk_styrke": 14
  },
  {
    "id": "tromso",
    "navn": "Tromsø IL",
    "kortnavn": "TIL",
    "by": "Tromsø",
    "divisjon": "Eliteserien",
    "sone": null,
    "stadion_navn": "Romssa Arena",
    "stadion_kapasitet": 7599,
    "stadion_standard": 4,
    "stadion_byggeaar": 1987,
    "rivaler": ["bodoglimt"],
    "historisk_styrke": 15
  },
  {
    "id": "aalesund",
    "navn": "Aalesunds FK",
    "kortnavn": "AAF",
    "by": "Ålesund",
    "divisjon": "Eliteserien",
    "sone": null,
    "stadion_navn": "Color Line Stadion",
    "stadion_kapasitet": 10778,
    "stadion_standard": 4,
    "stadion_byggeaar": 2005,
    "rivaler": ["molde", "hodd"],
    "historisk_styrke": 14
  },
  {
    "id": "start",
    "navn": "IK Start",
    "kortnavn": "STA",
    "by": "Kristiansand",
    "divisjon": "Eliteserien",
    "sone": null,
    "stadion_navn": "Sparebanken Sør Arena",
    "stadion_kapasitet": 14448,
    "stadion_standard": 4,
    "stadion_byggeaar": 2007,
    "rivaler": ["jerv", "viking", "floy"],
    "historisk_styrke": 15
  },
  {
    "id": "hamkam",
    "navn": "Hamarkameratene",
    "kortnavn": "HAM",
    "by": "Hamar",
    "divisjon": "Eliteserien",
    "sone": null,
    "stadion_navn": "Briskeby Stadion",
    "stadion_kapasitet": 7800,
    "stadion_standard": 3,
    "stadion_byggeaar": 1936,
    "rivaler": ["kongsvinger", "lillestrom", "elverum"],
    "historisk_styrke": 13
  },
  {
    "id": "kristiansund",
    "navn": "Kristiansund BK",
    "kortnavn": "KBK",
    "by": "Kristiansund",
    "divisjon": "Eliteserien",
    "sone": null,
    "stadion_navn": "Nordmøre Stadion",
    "stadion_kapasitet": 4444,
    "stadion_standard": 3,
    "stadion_byggeaar": 2007,
    "rivaler": ["molde", "aalesund"],
    "historisk_styrke": 12
  },
  {
    "id": "sandefjord",
    "navn": "Sandefjord Fotball",
    "kortnavn": "SAN",
    "by": "Sandefjord",
    "divisjon": "Eliteserien",
    "sone": null,
    "stadion_navn": "Jotun Arena",
    "stadion_kapasitet": 6582,
    "stadion_standard": 3,
    "stadion_byggeaar": 2008,
    "rivaler": ["odd", "framlarvik"],
    "historisk_styrke": 12
  },
  {
    "id": "kfum",
    "navn": "KFUM Oslo",
    "kortnavn": "KFU",
    "by": "Oslo",
    "divisjon": "Eliteserien",
    "sone": null,
    "stadion_navn": "KFUM Arena",
    "stadion_kapasitet": 1500,
    "stadion_standard": 2,
    "stadion_byggeaar": 2023,
    "rivaler": ["valerenga", "lyn", "skeid"],
    "historisk_styrke": 10
  },
  {
    "id": "odd",
    "navn": "Odds Ballklubb",
    "kortnavn": "ODD",
    "by": "Skien",
    "divisjon": "OBOS-ligaen",
    "sone": null,
    "stadion_navn": "Skagerak Arena",
    "stadion_kapasitet": 11767,
    "stadion_standard": 4,
    "stadion_byggeaar": 2007,
    "rivaler": ["sandefjord", "pors", "notodden"],
    "historisk_styrke": 16
  },
  {
    "id": "stromsgodset",
    "navn": "Strømsgodset IF",
    "kortnavn": "GOD",
    "by": "Drammen",
    "divisjon": "OBOS-ligaen",
    "sone": null,
    "stadion_navn": "Marienlyst Stadion",
    "stadion_kapasitet": 8935,
    "stadion_standard": 4,
    "stadion_byggeaar": 1924,
    "rivaler": ["mjondalen", "honefoss"],
    "historisk_styrke": 15
  },
  {
    "id": "haugesund",
    "navn": "FK Haugesund",
    "kortnavn": "HAU",
    "by": "Haugesund",
    "divisjon": "OBOS-ligaen",
    "sone": null,
    "stadion_navn": "Haugesund Sparebank Arena",
    "stadion_kapasitet": 8754,
    "stadion_standard": 4,
    "stadion_byggeaar": 1920,
    "rivaler": ["viking", "brann", "vardhaugesund"],
    "historisk_styrke": 15
  },
  {
    "id": "lyn",
    "navn": "Lyn 1896 FK",
    "kortnavn": "LYN",
    "by": "Oslo",
    "divisjon": "OBOS-ligaen",
    "sone": null,
    "stadion_navn": "Bislett Stadion",
    "stadion_kapasitet": 15400,
    "stadion_standard": 3,
    "stadion_byggeaar": 1922,
    "rivaler": ["valerenga", "skeid", "kfum"],
    "historisk_styrke": 15
  },
  {
    "id": "stabaek",
    "navn": "Stabæk Fotball",
    "kortnavn": "STB",
    "by": "Bærum",
    "divisjon": "OBOS-ligaen",
    "sone": null,
    "stadion_navn": "Nye Nadderud Stadion",
    "stadion_kapasitet": 8001,
    "stadion_standard": 4,
    "stadion_byggeaar": 1961,
    "rivaler": ["valerenga", "lyn", "baerum"],
    "historisk_styrke": 15
  },
  {
    "id": "sogndal",
    "navn": "Sogndal Fotball",
    "kortnavn": "SOG",
    "by": "Sogndal",
    "divisjon": "OBOS-ligaen",
    "sone": null,
    "stadion_navn": "Fosshaugane Campus",
    "stadion_kapasitet": 5622,
    "stadion_standard": 3,
    "stadion_byggeaar": 2006,
    "rivaler": ["brann", "aalesund", "førde"],
    "historisk_styrke": 14
  },
  {
    "id": "sandnesulf",
    "navn": "Sandnes Ulf",
    "kortnavn": "ULF",
    "by": "Sandnes",
    "divisjon": "OBOS-ligaen",
    "sone": null,
    "stadion_navn": "Øster Hus Arena",
    "stadion_kapasitet": 6043,
    "stadion_standard": 4,
    "stadion_byggeaar": 2020,
    "rivaler": ["viking", "bryne"],
    "historisk_styrke": 13
  },
  {
    "id": "kongsvinger",
    "navn": "Kongsvinger IL",
    "kortnavn": "KIL",
    "by": "Kongsvinger",
    "divisjon": "OBOS-ligaen",
    "sone": null,
    "stadion_navn": "Gjemselund Stadion",
    "stadion_kapasitet": 5824,
    "stadion_standard": 3,
    "stadion_byggeaar": 1953,
    "rivaler": ["hamkam", "elverum"],
    "historisk_styrke": 13
  },
  {
    "id": "bryne",
    "navn": "Bryne FK",
    "kortnavn": "BRY",
    "by": "Bryne",
    "divisjon": "OBOS-ligaen",
    "sone": null,
    "stadion_navn": "Bryne Stadion",
    "stadion_kapasitet": 5000,
    "stadion_standard": 3,
    "stadion_byggeaar": 1946,
    "rivaler": ["viking", "sandnesulf", "egersund"],
    "historisk_styrke": 13
  },
  {
    "id": "hodd",
    "navn": "IL Hødd",
    "kortnavn": "HOD",
    "by": "Ulsteinvik",
    "divisjon": "OBOS-ligaen",
    "sone": null,
    "stadion_navn": "Nye Høddvoll",
    "stadion_kapasitet": 4081,
    "stadion_standard": 3,
    "stadion_byggeaar": 2015,
    "rivaler": ["aalesund", "brattvag"],
    "historisk_styrke": 12
  },
  {
    "id": "asane",
    "navn": "Åsane Fotball",
    "kortnavn": "ASA",
    "by": "Bergen",
    "divisjon": "OBOS-ligaen",
    "sone": null,
    "stadion_navn": "Åsane Arena",
    "stadion_kapasitet": 3500,
    "stadion_standard": 3,
    "stadion_byggeaar": 2021,
    "rivaler": ["brann", "fana", "fyllingsdalen"],
    "historisk_styrke": 11
  },
  {
    "id": "moss",
    "navn": "Moss FK",
    "kortnavn": "MOS",
    "by": "Moss",
    "divisjon": "OBOS-ligaen",
    "sone": null,
    "stadion_navn": "Melløs Stadion",
    "stadion_kapasitet": 3170,
    "stadion_standard": 2,
    "stadion_byggeaar": 1939,
    "rivaler": ["fredrikstad", "sarpsborg08", "rade"],
    "historisk_styrke": 13
  },
  {
    "id": "ranheim",
    "navn": "Ranheim IL",
    "kortnavn": "RAN",
    "by": "Trondheim",
    "divisjon": "OBOS-ligaen",
    "sone": null,
    "stadion_navn": "EXTRA Arena",
    "stadion_kapasitet": 3000,
    "stadion_standard": 3,
    "stadion_byggeaar": 2010,
    "rivaler": ["rosenborg", "strindheim"],
    "historisk_styrke": 12
  },
  {
    "id": "raufoss",
    "navn": "Raufoss Fotball",
    "kortnavn": "RAU",
    "by": "Raufoss",
    "divisjon": "OBOS-ligaen",
    "sone": null,
    "stadion_navn": "Nammo Stadion",
    "stadion_kapasitet": 3000,
    "stadion_standard": 3,
    "stadion_byggeaar": 2015,
    "rivaler": ["gjoviklyn", "hamkam"],
    "historisk_styrke": 11
  },
  {
    "id": "strommen",
    "navn": "Strømmen IF",
    "kortnavn": "STR",
    "by": "Strømmen",
    "divisjon": "OBOS-ligaen",
    "sone": null,
    "stadion_navn": "Strømmen Stadion",
    "stadion_kapasitet": 2000,
    "stadion_standard": 2,
    "stadion_byggeaar": 1923,
    "rivaler": ["lillestrom", "mjondalen", "lorenskog"],
    "historisk_styrke": 11
  },
  {
    "id": "egersund",
    "navn": "Egersunds IK",
    "kortnavn": "EIK",
    "by": "Egersund",
    "divisjon": "OBOS-ligaen",
    "sone": null,
    "stadion_navn": "B&G Parken",
    "stadion_kapasitet": 1200,
    "stadion_standard": 2,
    "stadion_byggeaar": 1939,
    "rivaler": ["bryne", "viking"],
    "historisk_styrke": 9
  },
  {
    "id": "mjondalen",
    "navn": "Mjøndalen IF",
    "kortnavn": "MIF",
    "by": "Mjøndalen",
    "divisjon": "PostNord-ligaen",
    "sone": 1,
    "stadion_navn": "Consto Arena",
    "stadion_kapasitet": 4200,
    "stadion_standard": 3,
    "stadion_byggeaar": 1968,
    "rivaler": ["stromsgodset", "strommen"],
    "historisk_styrke": 14
  },
  {
    "id": "jerv",
    "navn": "FK Jerv",
    "kortnavn": "JER",
    "by": "Grimstad",
    "divisjon": "PostNord-ligaen",
    "sone": 1,
    "stadion_navn": "Levermyr Stadion",
    "stadion_kapasitet": 3458,
    "stadion_standard": 3,
    "stadion_byggeaar": 1983,
    "rivaler": ["arendal", "start", "floy"],
    "historisk_styrke": 13
  },
  {
    "id": "arendal",
    "navn": "Arendal Fotball",
    "kortnavn": "ARE",
    "by": "Arendal",
    "divisjon": "PostNord-ligaen",
    "sone": 1,
    "stadion_navn": "Norac Stadion",
    "stadion_kapasitet": 3238,
    "stadion_standard": 3,
    "stadion_byggeaar": 2017,
    "rivaler": ["jerv", "start"],
    "historisk_styrke": 11
  },
  {
    "id": "eiktonsberg",
    "navn": "FK Eik Tønsberg",
    "kortnavn": "EIK",
    "by": "Tønsberg",
    "divisjon": "PostNord-ligaen",
    "sone": 1,
    "stadion_navn": "Tønsberg Gressbane",
    "stadion_kapasitet": 5600,
    "stadion_standard": 3,
    "stadion_byggeaar": 1937,
    "rivaler": ["ornhorten", "framlarvik"],
    "historisk_styrke": 12
  },
  {
    "id": "pors",
    "navn": "Pors Fotball",
    "kortnavn": "POR",
    "by": "Porsgrunn",
    "divisjon": "PostNord-ligaen",
    "sone": 1,
    "stadion_navn": "Pors Stadion",
    "stadion_kapasitet": 3700,
    "stadion_standard": 2,
    "stadion_byggeaar": 1936,
    "rivaler": ["odd", "notodden", "framlarvik"],
    "historisk_styrke": 11
  },
  {
    "id": "kvikhalden",
    "navn": "Kvik Halden FK",
    "kortnavn": "KVI",
    "by": "Halden",
    "divisjon": "PostNord-ligaen",
    "sone": 1,
    "stadion_navn": "Halden Stadion",
    "stadion_kapasitet": 4200,
    "stadion_standard": 2,
    "stadion_byggeaar": 1930,
    "rivaler": ["sarpsborg08", "moss"],
    "historisk_styrke": 10
  },
  {
    "id": "notodden",
    "navn": "Notodden FK",
    "kortnavn": "NOT",
    "by": "Notodden",
    "divisjon": "PostNord-ligaen",
    "sone": 1,
    "stadion_navn": "Notodden Stadion",
    "stadion_kapasitet": 1700,
    "stadion_standard": 2,
    "stadion_byggeaar": 2008,
    "rivaler": ["odd", "pors"],
    "historisk_styrke": 11
  },
  {
    "id": "brattvag",
    "navn": "Brattvåg IL",
    "kortnavn": "BRA",
    "by": "Brattvåg",
    "divisjon": "PostNord-ligaen",
    "sone": 1,
    "stadion_navn": "Brattvåg Stadion",
    "stadion_kapasitet": 2000,
    "stadion_standard": 2,
    "stadion_byggeaar": 1990, "rivaler": ["hodd", "aalesund"],
    "historisk_styrke": 8
  },
  {
    "id": "vidar",
    "navn": "FK Vidar",
    "kortnavn": "VID",
    "by": "Stavanger",
    "divisjon": "PostNord-ligaen",
    "sone": 1,
    "stadion_navn": "Alustar Arena",
    "stadion_kapasitet": 5000,
    "stadion_standard": 2,
    "stadion_byggeaar": 1950,
    "rivaler": ["viking", "brodd", "hinna"],
    "historisk_styrke": 10
  },
  {
    "id": "sotra",
    "navn": "Sotra SK",
    "kortnavn": "SOT",
    "by": "Straume",
    "divisjon": "PostNord-ligaen",
    "sone": 1,
    "stadion_navn": "Straume Stadion",
    "stadion_kapasitet": 1300,
    "stadion_standard": 2,
    "stadion_byggeaar": 2013,
    "rivaler": ["asane", "lysekloster", "askoy"],
    "historisk_styrke": 8
  },
  {
    "id": "lysekloster",
    "navn": "Lysekloster IL",
    "kortnavn": "LYS",
    "by": "Os",
    "divisjon": "PostNord-ligaen",
    "sone": 1,
    "stadion_navn": "Lysekloster Family Arena",
    "stadion_kapasitet": 1500,
    "stadion_standard": 2,
    "stadion_byggeaar": 2015,
    "rivaler": ["os", "bjarg", "sandviken"],
    "historisk_styrke": 8
  },
  {
    "id": "sandviken",
    "navn": "IL Sandviken",
    "kortnavn": "SAN",
    "by": "Bergen",
    "divisjon": "PostNord-ligaen",
    "sone": 1,
    "stadion_navn": "Stemmemyren",
    "stadion_kapasitet": 1500,
    "stadion_standard": 2,
    "stadion_byggeaar": 1990,
    "rivaler": ["brann", "asane", "varegg"],
    "historisk_styrke": 7
  },
  {
    "id": "bjarg",
    "navn": "IL Bjarg",
    "kortnavn": "BJA",
    "by": "Bergen",
    "divisjon": "PostNord-ligaen",
    "sone": 1,
    "stadion_navn": "Stavollen Kunstgress",
    "stadion_kapasitet": 1200,
    "stadion_standard": 2,
    "stadion_byggeaar": 2000,
    "rivaler": ["fana", "sandviken", "gneist"],
    "historisk_styrke": 7
  },
  {
    "id": "traeff",
    "navn": "SK Træff",
    "kortnavn": "TRA",
    "by": "Molde",
    "divisjon": "PostNord-ligaen",
    "sone": 1,
    "stadion_navn": "Reknesbanen",
    "stadion_kapasitet": 1500,
    "stadion_standard": 2,
    "stadion_byggeaar": 2008,
    "rivaler": ["molde"],
    "historisk_styrke": 7
  },
  {
    "id": "skeid",
    "navn": "Skeid",
    "kortnavn": "SKE",
    "by": "Oslo",
    "divisjon": "PostNord-ligaen",
    "sone": 2,
    "stadion_navn": "Nordre Åsen",
    "stadion_kapasitet": 1600,
    "stadion_standard": 2,
    "stadion_byggeaar": 1950,
    "rivaler": ["kfum", "lyn", "kjelsas"],
    "historisk_styrke": 13
  },
  {
    "id": "ullkisa",
    "navn": "Ullensaker/Kisa IL",
    "kortnavn": "ULL",
    "by": "Jessheim",
    "divisjon": "PostNord-ligaen",
    "sone": 2,
    "stadion_navn": "Jessheim Stadion",
    "stadion_kapasitet": 4500,
    "stadion_standard": 3,
    "stadion_byggeaar": 2011,
    "rivaler": ["lillestrom", "eidsvoldturn"],
    "historisk_styrke": 12
  },
  {
    "id": "levanger",
    "navn": "Levanger FK",
    "kortnavn": "LEV",
    "by": "Levanger",
    "divisjon": "PostNord-ligaen",
    "sone": 2,
    "stadion_navn": "TOBB Arena Levanger",
    "stadion_kapasitet": 2400,
    "stadion_standard": 3,
    "stadion_byggeaar": 2000,
    "rivaler": ["stjordalsblink", "ranheim"],
    "historisk_styrke": 11
  },
  {
    "id": "kjelsas",
    "navn": "Kjelsås IL",
    "kortnavn": "KJE",
    "by": "Oslo",
    "divisjon": "PostNord-ligaen",
    "sone": 2,
    "stadion_navn": "Grefsen Stadion",
    "stadion_kapasitet": 4500,
    "stadion_standard": 2,
    "stadion_byggeaar": 1930,
    "rivaler": ["skeid", "grorud"],
    "historisk_styrke": 10
  },
  {
    "id": "grorud",
    "navn": "Grorud IL",
    "kortnavn": "GRO",
    "by": "Oslo",
    "divisjon": "PostNord-ligaen",
    "sone": 2,
    "stadion_navn": "Grorud Arctic Match",
    "stadion_kapasitet": 1700,
    "stadion_standard": 2,
    "stadion_byggeaar": 2010,
    "rivaler": ["kjelsas", "grei"],
    "historisk_styrke": 10
  },
  {
    "id": "tromsdalen",
    "navn": "Tromsdalen UIL",
    "kortnavn": "TUI",
    "by": "Tromsø",
    "divisjon": "PostNord-ligaen",
    "sone": 2,
    "stadion_navn": "TUIL Arena",
    "stadion_kapasitet": 3000,
    "stadion_standard": 2,
    "stadion_byggeaar": 2010,
    "rivaler": ["tromso", "floya", "skarp"],
    "historisk_styrke": 11
  },
  {
    "id": "stjordalsblink",
    "navn": "Stjørdals-Blink",
    "kortnavn": "STJ",
    "by": "Stjørdal",
    "divisjon": "PostNord-ligaen",
    "sone": 2,
    "stadion_navn": "M.U.S Stadion Sandskogan",
    "stadion_kapasitet": 2500,
    "stadion_standard": 2,
    "stadion_byggeaar": 2012,
    "rivaler": ["levanger", "ranheim"],
    "historisk_styrke": 10
  },
  {
    "id": "eidsvoldturn",
    "navn": "Eidsvold Turn",
    "kortnavn": "EID",
    "by": "Eidsvoll",
    "divisjon": "PostNord-ligaen",
    "sone": 2,
    "stadion_navn": "Myhrer Stadion",
    "stadion_kapasitet": 3000,
    "stadion_standard": 2,
    "stadion_byggeaar": 1970,
    "rivaler": ["ullkisa"],
    "historisk_styrke": 9
  },
  {
    "id": "honefoss",
    "navn": "Hønefoss BK",
    "kortnavn": "HON",
    "by": "Hønefoss",
    "divisjon": "PostNord-ligaen",
    "sone": 2,
    "stadion_navn": "AKA Arena",
    "stadion_kapasitet": 4256,
    "stadion_standard": 3,
    "stadion_byggeaar": 2009,
    "rivaler": ["stromsgodset", "mjondalen"],
    "historisk_styrke": 12
  },
  {
    "id": "follo",
    "navn": "Follo FK",
    "kortnavn": "FOL",
    "by": "Ski",
    "divisjon": "PostNord-ligaen",
    "sone": 2,
    "stadion_navn": "Ski Stadion",
    "stadion_kapasitet": 2500,
    "stadion_standard": 2,
    "stadion_byggeaar": 1956,
    "rivaler": ["kfum", "moss", "drobakfrogn"],
    "historisk_styrke": 10
  },
  {
    "id": "rana",
    "navn": "Rana FK",
    "kortnavn": "RAN",
    "by": "Mo i Rana",
    "divisjon": "PostNord-ligaen",
    "sone": 2,
    "stadion_navn": "Sagbakken Stadion",
    "stadion_kapasitet": 2000,
    "stadion_standard": 2,
    "stadion_byggeaar": 2009,
    "rivaler": ["junkeren"],
    "historisk_styrke": 7
  },
  {
    "id": "junkeren",
    "navn": "IK Junkeren",
    "kortnavn": "JUN",
    "by": "Bodø",
    "divisjon": "PostNord-ligaen",
    "sone": 2,
    "stadion_navn": "Nordlandshallen",
    "stadion_kapasitet": 6000,
    "stadion_standard": 3,
    "stadion_byggeaar": 1991,
    "rivaler": ["bodoglimt", "rana"],
    "historisk_styrke": 7
  },
  {
    "id": "lorenskog",
    "navn": "Lørenskog IF",
    "kortnavn": "LOR",
    "by": "Lørenskog",
    "divisjon": "PostNord-ligaen",
    "sone": 2,
    "stadion_navn": "Rolvsrud Stadion",
    "stadion_kapasitet": 2000,
    "stadion_standard": 2,
    "stadion_byggeaar": 1980,
    "rivaler": ["skjetten", "strommen", "lillestrom"],
    "historisk_styrke": 9
  },
  {
    "id": "trygglade",
    "navn": "SK Trygg/Lade",
    "kortnavn": "TRY",
    "by": "Trondheim",
    "divisjon": "PostNord-ligaen",
    "sone": 2,
    "stadion_navn": "OBOS Kunstgressbane",
    "stadion_kapasitet": 1000,
    "stadion_standard": 1,
    "stadion_byggeaar": 2005,
    "rivaler": ["ranheim", "strindheim", "byasen"],
    "historisk_styrke": 6
  },
  {
    "id": "asker",
    "navn": "Asker Fotball",
    "kortnavn": "ASK",
    "by": "Asker",
    "divisjon": "Norsk Tipping-ligaen",
    "sone": 1,
    "stadion_navn": "Føyka kunstgress",
    "stadion_kapasitet": 2000,
    "stadion_standard": 2,
    "stadion_byggeaar": 2000,
    "rivaler": ["baerum"],
    "historisk_styrke": 9
  },
  {
    "id": "baerum",
    "navn": "Bærum SK",
    "kortnavn": "BSK",
    "by": "Bærum",
    "divisjon": "Norsk Tipping-ligaen",
    "sone": 1,
    "stadion_navn": "Sandvika Stadion",
    "stadion_kapasitet": 1500,
    "stadion_standard": 2,
    "stadion_byggeaar": 2003,
    "rivaler": ["asker"],
    "historisk_styrke": 10
  },
  {
    "id": "frigg",
    "navn": "Frigg Oslo FK",
    "kortnavn": "FRI",
    "by": "Oslo",
    "divisjon": "Norsk Tipping-ligaen",
    "sone": 1,
    "stadion_navn": "Tørteberg Kunstgress",
    "stadion_kapasitet": 1000,
    "stadion_standard": 1,
    "stadion_byggeaar": 1990,
    "rivaler": ["lyn", "ready"],
    "historisk_styrke": 9
  },
  {
    "id": "gamleoslo",
    "navn": "FC Gamle Oslo",
    "kortnavn": "FGO",
    "by": "Oslo",
    "divisjon": "Norsk Tipping-ligaen",
    "sone": 1,
    "stadion_navn": "Vallhall Arena",
    "stadion_kapasitet": 5500,
    "stadion_standard": 3,
    "stadion_byggeaar": 2001,
    "rivaler": ["valerenga2", "unioncarlberner"],
    "historisk_styrke": 4
  },
  {
    "id": "grei",
    "navn": "SF Grei",
    "kortnavn": "GRE",
    "by": "Oslo",
    "divisjon": "Norsk Tipping-ligaen",
    "sone": 1,
    "stadion_navn": "Greibanen",
    "stadion_kapasitet": 1000,
    "stadion_standard": 1,
    "stadion_byggeaar": 1990,
    "rivaler": ["grorud"],
    "historisk_styrke": 5
  },
  {
    "id": "heming",
    "navn": "IL Heming",
    "kortnavn": "HEM",
    "by": "Oslo",
    "divisjon": "Norsk Tipping-ligaen",
    "sone": 1,
    "stadion_navn": "Heming idrettsanlegg",
    "stadion_kapasitet": 1000,
    "stadion_standard": 1,
    "stadion_byggeaar": 1980,
    "rivaler": ["ready"],
    "historisk_styrke": 4
  },
  {
    "id": "kfum2",
    "navn": "KFUM Oslo 2",
    "kortnavn": "KF2",
    "by": "Oslo",
    "divisjon": "Norsk Tipping-ligaen",
    "sone": 1,
    "stadion_navn": "KFUM Arena",
    "stadion_kapasitet": 1500,
    "stadion_standard": 2,
    "stadion_byggeaar": 2023,
    "rivaler": [],
    "historisk_styrke": 3
  },
  {
    "id": "konnerud",
    "navn": "Konnerud IL",
    "kortnavn": "KON",
    "by": "Drammen",
    "divisjon": "Norsk Tipping-ligaen",
    "sone": 1,
    "stadion_navn": "Konnerud stadion",
    "stadion_kapasitet": 1000,
    "stadion_standard": 1,
    "stadion_byggeaar": 1980,
    "rivaler": ["stromsgodset"],
    "historisk_styrke": 4
  },
  {
    "id": "lokomotivoslo",
    "navn": "Lokomotiv Oslo",
    "kortnavn": "LOK",
    "by": "Oslo",
    "divisjon": "Norsk Tipping-ligaen",
    "sone": 1,
    "stadion_navn": "Norges idrettshøgskole",
    "stadion_kapasitet": 1000,
    "stadion_standard": 1,
    "stadion_byggeaar": 1968,
    "rivaler": [],
    "historisk_styrke": 5
  },
  {
    "id": "nordstrand",
    "navn": "Nordstrand IF",
    "kortnavn": "NOR",
    "by": "Oslo",
    "divisjon": "Norsk Tipping-ligaen",
    "sone": 1,
    "stadion_navn": "Nordstrand idrettsanlegg",
    "stadion_kapasitet": 1000,
    "stadion_standard": 1,
    "stadion_byggeaar": 1970,
    "rivaler": ["kfum", "oppsal"],
    "historisk_styrke": 6
  },
  {
    "id": "ready",
    "navn": "IF Ready",
    "kortnavn": "REA",
    "by": "Oslo",
    "divisjon": "Norsk Tipping-ligaen",
    "sone": 1,
    "stadion_navn": "Gressbanen",
    "stadion_kapasitet": 1000,
    "stadion_standard": 1,
    "stadion_byggeaar": 1918,
    "rivaler": ["heming", "ullern"],
    "historisk_styrke": 5
  },
  {
    "id": "ullern",
    "navn": "Ullern IF",
    "kortnavn": "ULN",
    "by": "Oslo",
    "divisjon": "Norsk Tipping-ligaen",
    "sone": 1,
    "stadion_navn": "Ullern idrettsanlegg",
    "stadion_kapasitet": 1500,
    "stadion_standard": 1,
    "stadion_byggeaar": 1990,
    "rivaler": ["ready", "lyn"],
    "historisk_styrke": 7
  },
  {
    "id": "unioncarlberner",
    "navn": "Union Carl Berner",
    "kortnavn": "UCB",
    "by": "Oslo",
    "divisjon": "Norsk Tipping-ligaen",
    "sone": 1,
    "stadion_navn": "Jordal Idrettspark",
    "stadion_kapasitet": 1500,
    "stadion_standard": 1,
    "stadion_byggeaar": 2000,
    "rivaler": ["gamleoslo"],
    "historisk_styrke": 3
  },
  {
    "id": "valerenga2",
    "navn": "Vålerenga 2",
    "kortnavn": "VI2",
    "by": "Oslo",
    "divisjon": "Norsk Tipping-ligaen",
    "sone": 1,
    "stadion_navn": "Intility Arena",
    "stadion_kapasitet": 16555,
    "stadion_standard": 5,
    "stadion_byggeaar": 2017,
    "rivaler": [],
    "historisk_styrke": 4
  },
  {
    "id": "byasen",
    "navn": "Byåsen TF",
    "kortnavn": "BYA",
    "by": "Trondheim",
    "divisjon": "Norsk Tipping-ligaen",
    "sone": 2,
    "stadion_navn": "Byåsen Arena",
    "stadion_kapasitet": 500,
    "stadion_standard": 1,
    "stadion_byggeaar": 2007,
    "rivaler": ["nardo", "kolstad"],
    "historisk_styrke": 8
  },
  {
    "id": "kvik",
    "navn": "FK Kvik",
    "kortnavn": "FKK",
    "by": "Trondheim",
    "divisjon": "Norsk Tipping-ligaen",
    "sone": 2,
    "stadion_navn": "Rosenborgbanen",
    "stadion_kapasitet": 1000,
    "stadion_standard": 1,
    "stadion_byggeaar": 1980,
    "rivaler": ["rosenborg"],
    "historisk_styrke": 6
  },
  {
    "id": "melhus",
    "navn": "Melhus IL",
    "kortnavn": "MEL",
    "by": "Melhus",
    "divisjon": "Norsk Tipping-ligaen",
    "sone": 2,
    "stadion_navn": "Gruva Stadion",
    "stadion_kapasitet": 1000,
    "stadion_standard": 1,
    "stadion_byggeaar": 1990,
    "rivaler": ["orkla"],
    "historisk_styrke": 5
  },
  {
    "id": "nardo",
    "navn": "Nardo FK",
    "kortnavn": "NAR",
    "by": "Trondheim",
    "divisjon": "Norsk Tipping-ligaen",
    "sone": 2,
    "stadion_navn": "Nissekollen Kunstgress",
    "stadion_kapasitet": 1500,
    "stadion_standard": 2,
    "stadion_byggeaar": 1995,
    "rivaler": ["byasen", "strindheim"],
    "historisk_styrke": 8
  },
  {
    "id": "ntnui",
    "navn": "NTNUI Fotball",
    "kortnavn": "NTN",
    "by": "Trondheim",
    "divisjon": "Norsk Tipping-ligaen",
    "sone": 2,
    "stadion_navn": "Lade Kunstgress",
    "stadion_kapasitet": 1000,
    "stadion_standard": 1,
    "stadion_byggeaar": 2000,
    "rivaler": [],
    "historisk_styrke": 4
  },
  {
    "id": "orkla",
    "navn": "Orkla FK",
    "kortnavn": "ORK",
    "by": "Orkland",
    "divisjon": "Norsk Tipping-ligaen",
    "sone": 2,
    "stadion_navn": "Orkla Sparebank Stadion",
    "stadion_kapasitet": 1000,
    "stadion_standard": 1,
    "stadion_byggeaar": 2014,
    "rivaler": ["melhus"],
    "historisk_styrke": 6
  },
  {
    "id": "ranheim2",
    "navn": "Ranheim 2",
    "kortnavn": "RA2",
    "by": "Trondheim",
    "divisjon": "Norsk Tipping-ligaen",
    "sone": 2,
    "stadion_navn": "EXTRA Arena",
    "stadion_kapasitet": 3000,
    "stadion_standard": 3,
    "stadion_byggeaar": 2010,
    "rivaler": [],
    "historisk_styrke": 3
  },
  {
    "id": "rosenborg2",
    "navn": "Rosenborg 2",
    "kortnavn": "RB2",
    "by": "Trondheim",
    "divisjon": "Norsk Tipping-ligaen",
    "sone": 2,
    "stadion_navn": "SalMar Banen",
    "stadion_kapasitet": 1000,
    "stadion_standard": 2,
    "stadion_byggeaar": 2005,
    "rivaler": [],
    "historisk_styrke": 5
  },
  {
    "id": "strindheim",
    "navn": "Strindheim TF",
    "kortnavn": "STR",
    "by": "Trondheim",
    "divisjon": "Norsk Tipping-ligaen",
    "sone": 2,
    "stadion_navn": "Ruta Arena",
    "stadion_kapasitet": 1000,
    "stadion_standard": 1,
    "stadion_byggeaar": 2000,
    "rivaler": ["nardo", "byasen"],
    "historisk_styrke": 9
  },
  {
    "id": "herd",
    "navn": "SK Herd",
    "kortnavn": "HER",
    "by": "Ålesund",
    "divisjon": "Norsk Tipping-ligaen",
    "sone": 2,
    "stadion_navn": "AMFI Moa Stadion",
    "stadion_kapasitet": 10778,
    "stadion_standard": 4,
    "stadion_byggeaar": 2005,
    "rivaler": ["aalesund", "spjelkavik"],
    "historisk_styrke": 6
  },
  {
    "id": "spjelkavik",
    "navn": "Spjelkavik IL",
    "kortnavn": "SPJ",
    "by": "Ålesund",
    "divisjon": "Norsk Tipping-ligaen",
    "sone": 2,
    "stadion_navn": "Spjelkavik Stadion",
    "stadion_kapasitet": 1000,
    "stadion_standard": 1,
    "stadion_byggeaar": 1980,
    "rivaler": ["herd"],
    "historisk_styrke": 6
  },
  {
    "id": "aalesund2",
    "navn": "Aalesund 2",
    "kortnavn": "AA2",
    "by": "Ålesund",
    "divisjon": "Norsk Tipping-ligaen",
    "sone": 2,
    "stadion_navn": "Color Line Stadion",
    "stadion_kapasitet": 10778,
    "stadion_standard": 4,
    "stadion_byggeaar": 2005,
    "rivaler": [],
    "historisk_styrke": 4
  },
  {
    "id": "molde2",
    "navn": "Molde 2",
    "kortnavn": "MO2",
    "by": "Molde",
    "divisjon": "Norsk Tipping-ligaen",
    "sone": 2,
    "stadion_navn": "Aker Stadion",
    "stadion_kapasitet": 11800,
    "stadion_standard": 4,
    "stadion_byggeaar": 1998,
    "rivaler": [],
    "historisk_styrke": 4
  },
  {
    "id": "volda",
    "navn": "Volda TI",
    "kortnavn": "VOL",
    "by": "Volda",
    "divisjon": "Norsk Tipping-ligaen",
    "sone": 2,
    "stadion_navn": "Volda Stadion",
    "stadion_kapasitet": 1000,
    "stadion_standard": 1,
    "stadion_byggeaar": 1980,
    "rivaler": ["orsta"],
    "historisk_styrke": 5
  },
  {
    "id": "askoy",
    "navn": "Askøy FK",
    "kortnavn": "ASK",
    "by": "Askøy",
    "divisjon": "Norsk Tipping-ligaen",
    "sone": 3,
    "stadion_navn": "Tertnes Holdning Arena",
    "stadion_kapasitet": 1000,
    "stadion_standard": 1,
    "stadion_byggeaar": 2010,
    "rivaler": ["sotra"],
    "historisk_styrke": 5
  },
  {
    "id": "austevoll",
    "navn": "Austevoll IK",
    "kortnavn": "AUS",
    "by": "Austevoll",
    "divisjon": "Norsk Tipping-ligaen",
    "sone": 3,
    "stadion_navn": "Austevoll idrettsanlegg",
    "stadion_kapasitet": 1000,
    "stadion_standard": 1,
    "stadion_byggeaar": 1995,
    "rivaler": ["stord"],
    "historisk_styrke": 4
  },
  {
    "id": "brann2",
    "navn": "Brann 2",
    "kortnavn": "BR2",
    "by": "Bergen",
    "divisjon": "Norsk Tipping-ligaen",
    "sone": 3,
    "stadion_navn": "Varden Amfi",
    "stadion_kapasitet": 3500,
    "stadion_standard": 2,
    "stadion_byggeaar": 1990,
    "rivaler": [],
    "historisk_styrke": 4
  },
  {
    "id": "djerv1919",
    "navn": "SK Djerv 1919",
    "kortnavn": "DJE",
    "by": "Haugesund",
    "divisjon": "Norsk Tipping-ligaen",
    "sone": 3,
    "stadion_navn": "Djervbanen",
    "stadion_kapasitet": 1000,
    "stadion_standard": 1,
    "stadion_byggeaar": 1950,
    "rivaler": ["vardhaugesund", "haugesund"],
    "historisk_styrke": 8
  },
  {
    "id": "fana",
    "navn": "Fana IL",
    "kortnavn": "FAN",
    "by": "Bergen",
    "divisjon": "Norsk Tipping-ligaen",
    "sone": 3,
    "stadion_navn": "Nesttun idrettsplass",
    "stadion_kapasitet": 2500,
    "stadion_standard": 2,
    "stadion_byggeaar": 1940,
    "rivaler": ["fyllingsdalen", "bjarg", "gneist"],
    "historisk_styrke": 9
  },
  {
    "id": "fyllingsdalen",
    "navn": "FK Fyllingsdalen",
    "kortnavn": "FYL",
    "by": "Bergen",
    "divisjon": "Norsk Tipping-ligaen",
    "sone": 3,
    "stadion_navn": "Varden Amfi",
    "stadion_kapasitet": 3500,
    "stadion_standard": 2,
    "stadion_byggeaar": 1990,
    "rivaler": ["fana", "brann"],
    "historisk_styrke": 10
  },
  {
    "id": "forde",
    "navn": "Førde IL",
    "kortnavn": "FOR",
    "by": "Sunnfjord",
    "divisjon": "Norsk Tipping-ligaen",
    "sone": 3,
    "stadion_navn": "Førde stadion",
    "stadion_kapasitet": 3000,
    "stadion_standard": 2,
    "stadion_byggeaar": 1980,
    "rivaler": ["floro"],
    "historisk_styrke": 8
  },
  {
    "id": "gneist",
    "navn": "IL Gneist",
    "kortnavn": "GNE",
    "by": "Bergen",
    "divisjon": "Norsk Tipping-ligaen",
    "sone": 3,
    "stadion_navn": "Liland Kunstgress",
    "stadion_kapasitet": 1000,
    "stadion_standard": 1,
    "stadion_byggeaar": 2000,
    "rivaler": ["fana"],
    "historisk_styrke": 5
  },
  {
    "id": "os",
    "navn": "Os TF",
    "kortnavn": "OST",
    "by": "Bjørnafjorden",
    "divisjon": "Norsk Tipping-ligaen",
    "sone": 3,
    "stadion_navn": "Kuventræ",
    "stadion_kapasitet": 2300,
    "stadion_standard": 2,
    "stadion_byggeaar": 1980,
    "rivaler": ["lysekloster"],
    "historisk_styrke": 7
  },
  {
    "id": "sogndal2",
    "navn": "Sogndal 2",
    "kortnavn": "SO2",
    "by": "Sogndal",
    "divisjon": "Norsk Tipping-ligaen",
    "sone": 3,
    "stadion_navn": "Fosshaugane Campus",
    "stadion_kapasitet": 5622,
    "stadion_standard": 3,
    "stadion_byggeaar": 2006,
    "rivaler": [],
    "historisk_styrke": 3
  },
  {
    "id": "stord",
    "navn": "Stord Fotball",
    "kortnavn": "STO",
    "by": "Stord",
    "divisjon": "Norsk Tipping-ligaen",
    "sone": 3,
    "stadion_navn": "Stord stadion",
    "stadion_kapasitet": 1500,
    "stadion_standard": 2,
    "stadion_byggeaar": 1980,
    "rivaler": ["austevoll", "bremnes"],
    "historisk_styrke": 7
  },
  {
    "id": "vardhaugesund",
    "navn": "Vard Haugesund",
    "kortnavn": "VAR",
    "by": "Haugesund",
    "divisjon": "Norsk Tipping-ligaen",
    "sone": 3,
    "stadion_navn": "Haugesund Sparebank Arena",
    "stadion_kapasitet": 5200,
    "stadion_standard": 3,
    "stadion_byggeaar": 1920,
    "rivaler": ["haugesund", "djerv1919"],
    "historisk_styrke": 11
  },
  {
    "id": "varegg",
    "navn": "Varegg Fotball",
    "kortnavn": "VRG",
    "by": "Bergen",
    "divisjon": "Norsk Tipping-ligaen",
    "sone": 3,
    "stadion_navn": "Stemmemyren idrettsanlegg",
    "stadion_kapasitet": 1500,
    "stadion_standard": 2,
    "stadion_byggeaar": 1990,
    "rivaler": ["sandviken"],
    "historisk_styrke": 6
  },
  {
    "id": "asane2",
    "navn": "Åsane 2",
    "kortnavn": "AS2",
    "by": "Bergen",
    "divisjon": "Norsk Tipping-ligaen",
    "sone": 3,
    "stadion_navn": "Åsane Arena",
    "stadion_kapasitet": 3500,
    "stadion_standard": 3,
    "stadion_byggeaar": 2021,
    "rivaler": [],
    "historisk_styrke": 3
  },
  {
    "id": "brodd",
    "navn": "IL Brodd",
    "kortnavn": "BRO",
    "by": "Stavanger",
    "divisjon": "Norsk Tipping-ligaen",
    "sone": 4,
    "stadion_navn": "Midjord idrettspark",
    "stadion_kapasitet": 3000,
    "stadion_standard": 2,
    "stadion_byggeaar": 1950,
    "rivaler": ["vidar", "hinna"],
    "historisk_styrke": 6
  },
  {
    "id": "floy",
    "navn": "Fløy",
    "kortnavn": "FLO",
    "by": "Kristiansand",
    "divisjon": "Norsk Tipping-ligaen",
    "sone": 4,
    "stadion_navn": "Cemo Arena",
    "stadion_kapasitet": 2000,
    "stadion_standard": 2,
    "stadion_byggeaar": 2005,
    "rivaler": ["vindbjart", "start", "jerv"],
    "historisk_styrke": 9
  },
  {
    "id": "haugesund2",
    "navn": "Haugesund 2",
    "kortnavn": "HA2",
    "by": "Haugesund",
    "divisjon": "Norsk Tipping-ligaen",
    "sone": 4,
    "stadion_navn": "Haugesund Idrettsanlegg",
    "stadion_kapasitet": 1000,
    "stadion_standard": 1,
    "stadion_byggeaar": 1990,
    "rivaler": [],
    "historisk_styrke": 3
  },
  {
    "id": "hinna",
    "navn": "Hinna Fotball",
    "kortnavn": "HIN",
    "by": "Stavanger",
    "divisjon": "Norsk Tipping-ligaen",
    "sone": 4,
    "stadion_navn": "Hinna Arena",
    "stadion_kapasitet": 1000,
    "stadion_standard": 1,
    "stadion_byggeaar": 2000,
    "rivaler": ["madla", "brodd"],
    "historisk_styrke": 5
  },
  {
    "id": "madla",
    "navn": "Madla IL",
    "kortnavn": "MAD",
    "by": "Stavanger",
    "divisjon": "Norsk Tipping-ligaen",
    "sone": 4,
    "stadion_navn": "Madla Handelslag Stadion",
    "stadion_kapasitet": 1000,
    "stadion_standard": 1,
    "stadion_byggeaar": 2005,
    "rivaler": ["hinna"],
    "historisk_styrke": 5
  },
  {
    "id": "mandalskameratene",
    "navn": "Mandalskameratene",
    "kortnavn": "MK",
    "by": "Mandal",
    "divisjon": "Norsk Tipping-ligaen",
    "sone": 4,
    "stadion_navn": "Idrettsparken",
    "stadion_kapasitet": 4500,
    "stadion_standard": 2,
    "stadion_byggeaar": 1950,
    "rivaler": ["vindbjart"],
    "historisk_styrke": 10
  },
  {
    "id": "odd2",
    "navn": "Odd 2",
    "kortnavn": "OD2",
    "by": "Skien",
    "divisjon": "Norsk Tipping-ligaen",
    "sone": 4,
    "stadion_navn": "Skagerak Arena",
    "stadion_kapasitet": 11767,
    "stadion_standard": 4,
    "stadion_byggeaar": 2007,
    "rivaler": [],
    "historisk_styrke": 4
  },
  {
    "id": "stabaek2",
    "navn": "Stabæk 2",
    "kortnavn": "ST2",
    "by": "Bærum",
    "divisjon": "Norsk Tipping-ligaen",
    "sone": 4,
    "stadion_navn": "Nadderud kunstgress",
    "stadion_kapasitet": 1000,
    "stadion_standard": 1,
    "stadion_byggeaar": 2000,
    "rivaler": [],
    "historisk_styrke": 4
  },
  {
    "id": "staaljorpeland",
    "navn": "Staal Jørpeland",
    "kortnavn": "STA",
    "by": "Strand",
    "divisjon": "Norsk Tipping-ligaen",
    "sone": 4,
    "stadion_navn": "Jørpeland stadion",
    "stadion_kapasitet": 1500,
    "stadion_standard": 2,
    "stadion_byggeaar": 1980,
    "rivaler": ["viking", "vidar"],
    "historisk_styrke": 6
  },
  {
    "id": "varhaug",
    "navn": "Varhaug IL",
    "kortnavn": "VRH",
    "by": "Hå",
    "divisjon": "Norsk Tipping-ligaen",
    "sone": 4,
    "stadion_navn": "Alustar Arena",
    "stadion_kapasitet": 1000,
    "stadion_standard": 1,
    "stadion_byggeaar": 2010,
    "rivaler": ["naerbo"],
    "historisk_styrke": 4
  },
  {
    "id": "viking2",
    "navn": "Viking 2",
    "kortnavn": "VI2",
    "by": "Stavanger",
    "divisjon": "Norsk Tipping-ligaen",
    "sone": 4,
    "stadion_navn": "SR-Bank Arena",
    "stadion_kapasitet": 15900,
    "stadion_standard": 5,
    "stadion_byggeaar": 2004,
    "rivaler": [],
    "historisk_styrke": 5
  },
  {
    "id": "vindbjart",
    "navn": "Vindbjart FK",
    "kortnavn": "VIN",
    "by": "Vennesla",
    "divisjon": "Norsk Tipping-ligaen",
    "sone": 4,
    "stadion_navn": "Sparebanken Sør-banen",
    "stadion_kapasitet": 1500,
    "stadion_standard": 2,
    "stadion_byggeaar": 1990,
    "rivaler": ["floy", "mandalskameratene"],
    "historisk_styrke": 8
  },
  {
    "id": "vag",
    "navn": "Våg FK",
    "kortnavn": "VAG",
    "by": "Kristiansand",
    "divisjon": "Norsk Tipping-ligaen",
    "sone": 4,
    "stadion_navn": "Karruss Gressbane",
    "stadion_kapasitet": 1000,
    "stadion_standard": 1,
    "stadion_byggeaar": 1985,
    "rivaler": ["start"],
    "historisk_styrke": 5
  },
  {
    "id": "akra",
    "navn": "Åkra IL",
    "kortnavn": "AKR",
    "by": "Karmøy",
    "divisjon": "Norsk Tipping-ligaen",
    "sone": 4,
    "stadion_navn": "Åkra idrettspark",
    "stadion_kapasitet": 1000,
    "stadion_standard": 1,
    "stadion_byggeaar": 1980,
    "rivaler": ["kopervik", "djerv1919"],
    "historisk_styrke": 6
  },
  {
    "id": "alta",
    "navn": "Alta IF",
    "kortnavn": "ALT",
    "by": "Alta",
    "divisjon": "Norsk Tipping-ligaen",
    "sone": 5,
    "stadion_navn": "SmartDok Arena",
    "stadion_kapasitet": 1000,
    "stadion_standard": 2,
    "stadion_byggeaar": 2010,
    "rivaler": ["bossekop", "tromsdalen"],
    "historisk_styrke": 11
  },
  {
    "id": "bossekop",
    "navn": "Bossekop UL",
    "kortnavn": "BOS",
    "by": "Alta",
    "divisjon": "Norsk Tipping-ligaen",
    "sone": 5,
    "stadion_navn": "COOP Arena Kunstgress",
    "stadion_kapasitet": 1000,
    "stadion_standard": 1,
    "stadion_byggeaar": 2005,
    "rivaler": ["alta"],
    "historisk_styrke": 7
  },
  {
    "id": "fauskesprint",
    "navn": "Fauske/Sprint",
    "kortnavn": "FAU",
    "by": "Fauske",
    "divisjon": "Norsk Tipping-ligaen",
    "sone": 5,
    "stadion_navn": "SKS Arena",
    "stadion_kapasitet": 1000,
    "stadion_standard": 1,
    "stadion_byggeaar": 2010,
    "rivaler": ["bodoglimt"],
    "historisk_styrke": 5
  },
  {
    "id": "finnsnes",
    "navn": "Finnsnes IL",
    "kortnavn": "FIN",
    "by": "Senja",
    "divisjon": "Norsk Tipping-ligaen",
    "sone": 5,
    "stadion_navn": "Finnsnes Stadion",
    "stadion_kapasitet": 1000,
    "stadion_standard": 2,
    "stadion_byggeaar": 1980,
    "rivaler": ["senja", "tromsdalen"],
    "historisk_styrke": 8
  },
  {
    "id": "floya",
    "navn": "IF Fløya",
    "kortnavn": "FLY",
    "by": "Tromsø",
    "divisjon": "Norsk Tipping-ligaen",
    "sone": 5,
    "stadion_navn": "Fløya Arena",
    "stadion_kapasitet": 600,
    "stadion_standard": 1,
    "stadion_byggeaar": 2005,
    "rivaler": ["tromsdalen", "skarp", "tromso"],
    "historisk_styrke": 8
  },
  {
    "id": "harstad",
    "navn": "Harstad IL",
    "kortnavn": "HAR",
    "by": "Harstad",
    "divisjon": "Norsk Tipping-ligaen",
    "sone": 5,
    "stadion_navn": "Harstad stadion",
    "stadion_kapasitet": 700,
    "stadion_standard": 1,
    "stadion_byggeaar": 1970,
    "rivaler": ["mjolner"],
    "historisk_styrke": 9
  },
  {
    "id": "kongsvinger2",
    "navn": "Kongsvinger 2",
    "kortnavn": "KI2",
    "by": "Kongsvinger",
    "divisjon": "Norsk Tipping-ligaen",
    "sone": 5,
    "stadion_navn": "Gjemselund stadion",
    "stadion_kapasitet": 5824,
    "stadion_standard": 3,
    "stadion_byggeaar": 1953,
    "rivaler": [],
    "historisk_styrke": 3
  },
  {
    "id": "lillestrom2",
    "navn": "Lillestrøm 2",
    "kortnavn": "LS2",
    "by": "Lillestrøm",
    "divisjon": "Norsk Tipping-ligaen",
    "sone": 5,
    "stadion_navn": "LSK-Hallen",
    "stadion_kapasitet": 1500,
    "stadion_standard": 2,
    "stadion_byggeaar": 2007,
    "rivaler": [],
    "historisk_styrke": 4
  },
  {
    "id": "skedsmo",
    "navn": "Skedsmo FK",
    "kortnavn": "SKE",
    "by": "Lillestrøm",
    "divisjon": "Norsk Tipping-ligaen",
    "sone": 5,
    "stadion_navn": "Skedsmo Stadion",
    "stadion_kapasitet": 2000,
    "stadion_standard": 2,
    "stadion_byggeaar": 1980,
    "rivaler": ["skjetten", "lillestrom"],
    "historisk_styrke": 6
  },
  {
    "id": "skjervoy",
    "navn": "Skjervøy IK",
    "kortnavn": "SKJ",
    "by": "Skjervøy",
    "divisjon": "Norsk Tipping-ligaen",
    "sone": 5,
    "stadion_navn": "Lerøy Stadion",
    "stadion_kapasitet": 1000,
    "stadion_standard": 1,
    "stadion_byggeaar": 2000,
    "rivaler": ["floya"],
    "historisk_styrke": 7
  },
  {
    "id": "skjetten",
    "navn": "Skjetten Fotball",
    "kortnavn": "SKT",
    "by": "Lillestrøm",
    "divisjon": "Norsk Tipping-ligaen",
    "sone": 5,
    "stadion_navn": "Skjetten Stadion",
    "stadion_kapasitet": 2500,
    "stadion_standard": 2,
    "stadion_byggeaar": 1980,
    "rivaler": ["skedsmo", "lorenskog"],
    "historisk_styrke": 7
  },
  {
    "id": "stromsgodset2",
    "navn": "Strømsgodset 2",
    "kortnavn": "GO2",
    "by": "Drammen",
    "divisjon": "Norsk Tipping-ligaen",
    "sone": 5,
    "stadion_navn": "Marienlyst stadion",
    "stadion_kapasitet": 8935,
    "stadion_standard": 4,
    "stadion_byggeaar": 1924,
    "rivaler": [],
    "historisk_styrke": 4
  },
  {
    "id": "tromso2",
    "navn": "Tromsø 2",
    "kortnavn": "TI2",
    "by": "Tromsø",
    "divisjon": "Norsk Tipping-ligaen",
    "sone": 5,
    "stadion_navn": "Romssa Arena",
    "stadion_kapasitet": 7599,
    "stadion_standard": 4,
    "stadion_byggeaar": 1987,
    "rivaler": [],
    "historisk_styrke": 4
  },
  {
    "id": "ulfstind",
    "navn": "IL Ulfstind",
    "kortnavn": "ULF",
    "by": "Tromsø",
    "divisjon": "Norsk Tipping-ligaen",
    "sone": 5,
    "stadion_navn": "Tønsnes kunstgressbane",
    "stadion_kapasitet": 1000,
    "stadion_standard": 1,
    "stadion_byggeaar": 2012,
    "rivaler": ["floya", "skarp"],
    "historisk_styrke": 4
  },
  {
    "id": "bjorkelangen",
    "navn": "Bjørkelangen SF",
    "kortnavn": "BJO",
    "by": "Aurskog-Høland",
    "divisjon": "Norsk Tipping-ligaen",
    "sone": 6,
    "stadion_navn": "Bjørkelangen kunstgress",
    "stadion_kapasitet": 1000,
    "stadion_standard": 1,
    "stadion_byggeaar": 2000,
    "rivaler": ["ahfk"],
    "historisk_styrke": 4
  },
  {
    "id": "brumunddal",
    "navn": "Brumunddal Fotball",
    "kortnavn": "BRU",
    "by": "Ringsaker",
    "divisjon": "Norsk Tipping-ligaen",
    "sone": 6,
    "stadion_navn": "Sveum Idrettspark",
    "stadion_kapasitet": 2000,
    "stadion_standard": 2,
    "stadion_byggeaar": 1980,
    "rivaler": ["elverum", "raufoss", "lillehammer"],
    "historisk_styrke": 8
  },
  {
    "id": "drobakfrogn",
    "navn": "Drøbak-Frogn",
    "kortnavn": "DFI",
    "by": "Frogn",
    "divisjon": "Norsk Tipping-ligaen",
    "sone": 6,
    "stadion_navn": "Seiersten stadion",
    "stadion_kapasitet": 1500,
    "stadion_standard": 2,
    "stadion_byggeaar": 1980,
    "rivaler": ["follo", "moss"],
    "historisk_styrke": 9
  },
  {
    "id": "elverum",
    "navn": "Elverum Fotball",
    "kortnavn": "ELV",
    "by": "Elverum",
    "divisjon": "Norsk Tipping-ligaen",
    "sone": 6,
    "stadion_navn": "Elverum stadion",
    "stadion_kapasitet": 1400,
    "stadion_standard": 2,
    "stadion_byggeaar": 1950,
    "rivaler": ["brumunddal", "hamkam"],
    "historisk_styrke": 9
  },
  {
    "id": "framlarvik",
    "navn": "IF Fram Larvik",
    "kortnavn": "FRA",
    "by": "Larvik",
    "divisjon": "Norsk Tipping-ligaen",
    "sone": 6,
    "stadion_navn": "Framparken",
    "stadion_kapasitet": 2500,
    "stadion_standard": 2,
    "stadion_byggeaar": 1930,
    "rivaler": ["ornhorten", "pors", "odd"],
    "historisk_styrke": 10
  },
  {
    "id": "gjoviklyn",
    "navn": "FK Gjøvik-Lyn",
    "kortnavn": "GJO",
    "by": "Gjøvik",
    "divisjon": "Norsk Tipping-ligaen",
    "sone": 6,
    "stadion_navn": "Gjøvik Stadion",
    "stadion_kapasitet": 3000,
    "stadion_standard": 2,
    "stadion_byggeaar": 1980,
    "rivaler": ["raufoss", "lillehammer"],
    "historisk_styrke": 8
  },
  {
    "id": "lillehammer",
    "navn": "Lillehammer FK",
    "kortnavn": "LIL",
    "by": "Lillehammer",
    "divisjon": "Norsk Tipping-ligaen",
    "sone": 6,
    "stadion_navn": "Jorekstad",
    "stadion_kapasitet": 1000,
    "stadion_standard": 1,
    "stadion_byggeaar": 1985,
    "rivaler": ["brumunddal", "gjoviklyn"],
    "historisk_styrke": 7
  },
  {
    "id": "lyn2",
    "navn": "Lyn 2",
    "kortnavn": "LY2",
    "by": "Oslo",
    "divisjon": "Norsk Tipping-ligaen",
    "sone": 6,
    "stadion_navn": "Kringsjå kunstgress",
    "stadion_kapasitet": 1000,
    "stadion_standard": 1,
    "stadion_byggeaar": 2000,
    "rivaler": [],
    "historisk_styrke": 4
  },
  {
    "id": "oppsal",
    "navn": "Oppsal IF",
    "kortnavn": "OPP",
    "by": "Oslo",
    "divisjon": "Norsk Tipping-ligaen",
    "sone": 6,
    "stadion_navn": "Trasop kunstgress",
    "stadion_kapasitet": 1000,
    "stadion_standard": 1,
    "stadion_byggeaar": 2000,
    "rivaler": ["kfum", "nordstrand"],
    "historisk_styrke": 6
  },
  {
    "id": "ralingen",
    "navn": "Rælingen FK",
    "kortnavn": "RAL",
    "by": "Rælingen",
    "divisjon": "Norsk Tipping-ligaen",
    "sone": 6,
    "stadion_navn": "Marikollen Idrettspark",
    "stadion_kapasitet": 1000,
    "stadion_standard": 1,
    "stadion_byggeaar": 1990,
    "rivaler": ["skjetten", "lorenskog"],
    "historisk_styrke": 4
  },
  {
    "id": "rade",
    "navn": "Råde IL",
    "kortnavn": "RAD",
    "by": "Råde",
    "divisjon": "Norsk Tipping-ligaen",
    "sone": 6,
    "stadion_navn": "Råde idrettspark",
    "stadion_kapasitet": 1000,
    "stadion_standard": 1,
    "stadion_byggeaar": 1980,
    "rivaler": ["moss", "fredrikstad"],
    "historisk_styrke": 5
  },
  {
    "id": "sandefjord2",
    "navn": "Sandefjord 2",
    "kortnavn": "SA2",
    "by": "Sandefjord",
    "divisjon": "Norsk Tipping-ligaen",
    "sone": 6,
    "stadion_navn": "Storstadion",
    "stadion_kapasitet": 2000,
    "stadion_standard": 2,
    "stadion_byggeaar": 1960,
    "rivaler": [],
    "historisk_styrke": 3
  },
  {
    "id": "sarpsborg082",
    "navn": "Sarpsborg 08 2",
    "kortnavn": "S82",
    "by": "Sarpsborg",
    "divisjon": "Norsk Tipping-ligaen",
    "sone": 6,
    "stadion_navn": "Sarpsborg Stadion",
    "stadion_kapasitet": 8022,
    "stadion_standard": 4,
    "stadion_byggeaar": 1930,
    "rivaler": [],
    "historisk_styrke": 3
  },
  {
    "id": "ornhorten",
    "navn": "Ørn Horten",
    "kortnavn": "ORN",
    "by": "Horten",
    "divisjon": "Norsk Tipping-ligaen",
    "sone": 6,
    "stadion_navn": "Lystlunden Stadion",
    "stadion_kapasitet": 3000,
    "stadion_standard": 2,
    "stadion_byggeaar": 1940,
    "rivaler": ["framlarvik", "eiktonsberg"],
    "historisk_styrke": 11
  }
]
